[
  {
    "id": "c8bb0a36-344f-4260-b37e-fbd6f382cd75",
    "title": "七帝お疲れ様☆",
    "tags": [
      "binwan-tohoku#jugem",
      "☆ayaka☆"
    ],
    "url": "http://binwan-tohoku.jugem.jp/?page=20",
    "contents": "山中湖で、おでこと首と○○という、\r\n何とも目立つ場所ばかり刺されてきた彩花です\r\n\r\n大分落ち着きましたが、見事に赤くなってしまったので、\r\n見て誤解を招かないようにここに書いておきます。\r\n\r\n\r\n虫刺されです\r\n\r\n\r\n\r\n＝＝＝\r\n\r\nさて、昨日で七帝も終了♪\r\nBチームの皆さん、コーチ、そして1年マネの皆、\r\n本当にお疲れ様でした！！\r\n\r\n\r\n初めての1年生だけの試合。\r\n「かわいい子には旅をさせよ」ということで、涙をのんで厳しい選択をしたのです\r\n\r\n…が！！向上心高い彼女たち☆\r\nしっかり、大役を果たしてくれたようです\r\n\r\n\r\n\r\n実習と卒研のため仙台に残った真理が、\r\nメールで報告してくれました。\r\n\r\n＞1年生は本当によくがんばっていました\r\n＞うち居なくても良かったんじゃないかと\r\n＞思うくらいです（笑）\r\n\r\n\r\n\r\n\r\n\r\n\r\n七帝までの1週間、彼女たちは本当に七帝に備え、\r\n一生懸命準備をしていました。\r\n\r\n▼まずはつり防止のキネシオの習得\r\n（シフトの都合上、私が教えたのはさきとひろこだったので\r\n2人の写真に。ごめんね）\r\n\r\n\r\n\r\n\r\nさーて、誰が貼られる人になろうか。\r\n▼最初はひろこを指名。\r\n\r\n\r\n\r\n\r\n\r\n「何してるの！？」\r\n\r\n「いや、私の足くさくないかとおもって…」\r\n\r\nやっぱり彼女は面白いです\r\n\r\n\r\n\r\n▼ポイントを押さえペターと貼る。\r\n\r\n\r\n\r\n\r\n\r\n\r\n\r\n見事1日でマスターしてくれました\r\n七帝でもキネシオ貼りは大活躍してくれたそうです\r\n\r\n\r\n\r\n\r\nこのほかにも、\r\n「あやかさんがテーピング巻いているところを見ていてもいいですか？」\r\nとわかな。\r\n\r\n「私の付けたスコアチェックしてくれますか？」\r\nとゆうこ。\r\n\r\n「山中湖前にすみません！ルールで確認したいことがあるのですが…」\r\nとメールしてきたさき。\r\n\r\n「まだまだ半人前なので、早く仕事ができるようになりたいです！」\r\nとゆきの。\r\n\r\n\r\n\r\n\r\n\r\n一生懸命な彼女たちを見て、\r\n自分の1年生の頃の七帝を思い出しました。\r\n\r\nin福岡。\r\n暑くて、初めて1年生だけで仕事して、\r\n正直色々大変な部分もあったけど、\r\nあれを経験して初めて「男ラクのマネージャー」になれた気がした。\r\n\r\n（様々な方々に迷惑を掛けたのは事実です…\r\n当時の七帝CAPWがいさん、現M1,M2の先輩方、\r\nあの時は本当にありがとうございました！\r\n今となっては、私のラクロスLifeのBEST３に入る良い思い出です♪）\r\n\r\n\r\n\r\n\r\n今年も、そんな達成感を味わってくれていたら良いな♪\r\nゆっくり、七帝のお話聞かせてね",
    "article_datetime": "2008-08-12 16:00:00 +0900",
    "secure_type": 0,
    "created_datetime": "2023-11-04 06:11:55 +0900"
  },
  {
    "id": "24952d0b-c30e-4804-ac0d-4f1952de1c02",
    "title": "イベント終了",
    "tags": [
      "binwan-tohoku#jugem"
    ],
    "url": "http://binwan-tohoku.jugem.jp/?page=20",
    "contents": "みなさん！山中湖おつかれさまでした◎\r\n\r\n\r\nそして今日、七帝組も終わります。\r\n\r\n\r\n\r\nどちらも運営面でがんばってくれた方々、ありがとうございました\r\n\r\n\r\n\r\n\r\n\r\n昨日は、七帝のレセプションに参加！\r\n\r\nほんとは、\r\n\r\nイケメン探しと、\r\n\r\n９大のエースを酒でつぶしてお持ち帰る\r\n\r\n\r\nっていうのが名目（うそです）だったんですが、\r\n\r\n\r\n\r\n\r\nビールを持って踏み込んだ地は…\r\n\r\n\r\nすでに試合の終わった名大でした。\r\n\r\n\r\n\r\n\r\nそしてそこには、このブログを読んでいるっていう方が！！\r\n\r\n実際それってすごくないっすか！！\r\n\r\n\r\n\r\nめっちゃ感動すべきところでしたが、\r\n\r\nかなりお酒が入っていて、ちゃんと感動を伝えることができませんでした。\r\nすみません。\r\n\r\nいや〜うれしいです\r\n\r\n\r\n（約束どおり、ブログに書きましたよ）\r\n\r\n\r\n\r\n\r\n\r\n\r\n山中湖も、七帝も写真いろいろ載せたいのですが、おいおい…\r\n\r\n\r\n\r\n\r\n今日は「お疲れ様スペシャル」で！\r\n\r\n\r\n\r\nまずは…\r\n\r\n\r\n\r\n\r\n\r\nわれらが山中湖係大上さん\r\n\r\n\r\n\r\n\r\n４日目なんで、見るからに、疲労困憊のご様子…\r\n\r\n\r\n本当にお疲れ様でした\r\n\r\n\r\n\r\nそして、\r\n\r\n片道７時間を共にし、遠いところまできてくださったコーチの方々",
    "article_datetime": "2008-08-11 16:00:00 +0900",
    "secure_type": 0,
    "created_datetime": "2023-11-04 06:11:55 +0900"
  }
]