[
  {
    "id": "00dbfbe5-cb34-4f9d-885e-d4755c697710",
    "title": "新年会",
    "tags": [
      "binwan-tohoku#jugem",
      "☆atsuko☆"
    ],
    "url": "http://binwan-tohoku.jugem.jp/?page=9",
    "contents": "有言実行目指しています。たぶん、たいちゃんしかわかりませんが…本日マネ新年会がありました！大御所2人と、新ポジリと、若い子2人の5人でしたが、長老まりりんの暴走もあって、なかなか楽しい会でしたね◎今日これなかった人…かわいそうです！場所は、ゆりかと吉岡のバイト先の近く、コローレというお店です。料理もおいしいし、店員さんもすごくいい人なので、オススメですみなさんゼヒ行ってみてください！にしても、今日気づいたことは、「あたしって…騙されやすい人間だ」っていうこと。みんなだますの上手いです。嘘はよくないです。絶対に。本日の主役の大御所2人彩花さんが、すっかり大人の色気出してました。『脱アヒル』だそうで。まりりんは、言わずもがな、平然と暴走してました。もう２４歳ですもんね。幹事おつかれ〜ひろこ。頼まなくてものろけるサキタス。みんな髪、茶色くていいな〜の写真あやかさんとゆうこの引っ越しが順調に終わりますように！\r\n \r\n ",
    "article_datetime": "2009-02-07 17:00:00 +0900",
    "secure_type": 0,
    "created_datetime": "2023-11-04 06:11:46 +0900"
  },
  {
    "id": "ced07f61-7c87-4711-8171-e1697c777f92",
    "title": "スタッフのアパレル",
    "tags": [
      "binwan-tohoku#jugem"
    ],
    "url": "http://binwan-tohoku.jugem.jp/?page=9",
    "contents": "今日でテストが終わって、私を阻む足かせは何もなくなりました。私がこんな時真っ先に足を運ぶのは・・・UNIQLOです。なんとカラフルなアパレルたち・・・本当に心が癒されますね。で、本題の今年度のスタッフアパレルですが、カラフルではなく、広い試合会場でも可視光線を反射しまくって目立つことうけあいな白！そして上下揃い！でいこう！とマネージャー軍団は考えていますコーチの皆さんの意見はいかがでしょう？やっぱり全日の会場とか行くと、上下揃いのジャージを着てる大学は目立ちますし、",
    "article_datetime": "2009-02-06 17:00:00 +0900",
    "secure_type": 0,
    "created_datetime": "2023-11-04 06:11:46 +0900"
  }
]